[
  {
    "ticker": "COALINDIA.NS",
    "name": "COAL INDIA LTD",
    "sector": "Energy",
    "price": 481.6,
    "score": 96.3,
    "category": "Non-Banking",
    "metrics": {
      "roe": 28.12,
      "roa": 7.12,
      "pe": 9.54,
      "pb": 2.49,
      "ev_ebitda": 6.21,
      "growth": 16.2,
      "margins": 24.49,
      "de": 12.0,
      "momentum": 24.86
    },
    "rank": 1,
    "percentiles": {
      "roe": 83.3,
      "roa": 58.3,
      "pe": 100.0,
      "pb": 83.3,
      "ev_ebitda": 25.0,
      "growth": 58.3,
      "margins": 75.0,
      "de": 54.2,
      "momentum": 87.5
    }
  },
  {
    "ticker": "SHRIRAMFIN.NS",
    "name": "SHRIRAM FINANCE LIMITED",
    "sector": "Financial Services",
    "price": 938.5,
    "score": 82.0,
    "category": "Banking & Finance",
    "metrics": {
      "roe": 16.38,
      "roa": 3.26,
      "pe": 17.63,
      "pb": 2.68,
      "ev_ebitda": 0,
      "growth": 16.7,
      "margins": 0.0,
      "de": 275.0,
      "momentum": 49.06
    },
    "rank": 2,
    "percentiles": {
      "roe": 54.2,
      "roa": 25.0,
      "pe": 75.0,
      "pb": 75.0,
      "ev_ebitda": 0.0,
      "growth": 62.5,
      "margins": 0.0,
      "de": 8.3,
      "momentum": 95.8
    }
  },
  {
    "ticker": "ULTRACEMCO.NS",
    "name": "ULTRATECH CEMENT LIMITED",
    "sector": "Basic Materials",
    "price": 11597.0,
    "score": 78.94,
    "category": "Non-Banking",
    "metrics": {
      "roe": 10.59,
      "roa": 5.62,
      "pe": 41.88,
      "pb": 4.74,
      "ev_ebitda": 0,
      "growth": 3.0,
      "margins": 19.23,
      "de": 29.0,
      "momentum": -0.72
    },
    "rank": 3,
    "percentiles": {
      "roe": 4.2,
      "roa": 41.7,
      "pe": 25.0,
      "pb": 50.0,
      "ev_ebitda": 0.0,
      "growth": 16.7,
      "margins": 54.2,
      "de": 37.5,
      "momentum": 50.0
    }
  },
  {
    "ticker": "DRREDDY.NS",
    "name": "DR. REDDY S LABORATORIES",
    "sector": "Healthcare",
    "price": 1325.0,
    "score": 73.67,
    "category": "Non-Banking",
    "metrics": {
      "roe": 16.1,
      "roa": 7.96,
      "pe": 19.53,
      "pb": 2.96,
      "ev_ebitda": 12.86,
      "growth": 4.4,
      "margins": 24.52,
      "de": 18.0,
      "momentum": 12.94
    },
    "rank": 4,
    "percentiles": {
      "roe": 45.8,
      "roa": 66.7,
      "pe": 66.7,
      "pb": 70.8,
      "ev_ebitda": 45.8,
      "growth": 25.0,
      "margins": 79.2,
      "de": 45.8,
      "momentum": 79.2
    }
  },
  {
    "ticker": "NESTLEIND.NS",
    "name": "NESTLE INDIA LIMITED",
    "sector": "Consumer Defensive",
    "price": 1463.8,
    "score": 71.13,
    "category": "Non-Banking",
    "metrics": {
      "roe": 76.34,
      "roa": 22.69,
      "pe": 80.92,
      "pb": 54.74,
      "ev_ebitda": 52.84,
      "growth": 23.8,
      "margins": 22.92,
      "de": 9.0,
      "momentum": 25.3
    },
    "rank": 5,
    "percentiles": {
      "roe": 95.8,
      "roa": 91.7,
      "pe": 8.3,
      "pb": 4.2,
      "ev_ebitda": 79.2,
      "growth": 79.2,
      "margins": 66.7,
      "de": 66.7,
      "momentum": 91.7
    }
  },
  {
    "ticker": "TCS.NS",
    "name": "TATA CONSULTANCY SERV LT",
    "sector": "Technology",
    "price": 2474.8,
    "score": 69.1,
    "category": "Non-Banking",
    "metrics": {
      "roe": 48.4,
      "roa": 24.43,
      "pe": 18.19,
      "pb": 7.89,
      "ev_ebitda": 11.89,
      "growth": 9.6,
      "margins": 27.11,
      "de": 10.0,
      "momentum": -28.38
    },
    "rank": 6,
    "percentiles": {
      "roe": 91.7,
      "roa": 95.8,
      "pe": 70.8,
      "pb": 25.0,
      "ev_ebitda": 33.3,
      "growth": 45.8,
      "margins": 83.3,
      "de": 62.5,
      "momentum": 0.0
    }
  },
  {
    "ticker": "AXISBANK.NS",
    "name": "AXIS BANK LIMITED",
    "sector": "Financial Services",
    "price": 1275.5,
    "score": 68.88,
    "category": "Banking & Finance",
    "metrics": {
      "roe": 13.15,
      "roa": 1.47,
      "pe": 15.1,
      "pb": 1.84,
      "ev_ebitda": 0,
      "growth": -11.2,
      "margins": 0.0,
      "de": 0,
      "momentum": 8.11
    },
    "rank": 7,
    "percentiles": {
      "roe": 12.5,
      "roa": 8.3,
      "pe": 95.8,
      "pb": 100.0,
      "ev_ebitda": 0.0,
      "growth": 8.3,
      "margins": 0.0,
      "de": 100.0,
      "momentum": 75.0
    }
  },
  {
    "ticker": "ADANIPORTS.NS",
    "name": "ADANI PORT & SEZ LTD",
    "sector": "Industrials",
    "price": 1675.5,
    "score": 67.03,
    "category": "Non-Banking",
    "metrics": {
      "roe": 15.59,
      "roa": 6.76,
      "pe": 28.8,
      "pb": 5.4,
      "ev_ebitda": 19.18,
      "growth": 26.5,
      "margins": 58.99,
      "de": 64.0,
      "momentum": 23.03
    },
    "rank": 8,
    "percentiles": {
      "roe": 41.7,
      "roa": 50.0,
      "pe": 45.8,
      "pb": 37.5,
      "ev_ebitda": 62.5,
      "growth": 83.3,
      "margins": 95.8,
      "de": 25.0,
      "momentum": 83.3
    }
  },
  {
    "ticker": "WIPRO.NS",
    "name": "WIPRO LTD",
    "sector": "Technology",
    "price": 201.2,
    "score": 66.64,
    "category": "Non-Banking",
    "metrics": {
      "roe": 15.49,
      "roa": 6.86,
      "pe": 16.02,
      "pb": 2.35,
      "ev_ebitda": 10.01,
      "growth": 7.7,
      "margins": 19.06,
      "de": 23.0,
      "momentum": -17.62
    },
    "rank": 9,
    "percentiles": {
      "roe": 37.5,
      "roa": 54.2,
      "pe": 87.5,
      "pb": 87.5,
      "ev_ebitda": 29.2,
      "growth": 41.7,
      "margins": 50.0,
      "de": 41.7,
      "momentum": 25.0
    }
  },
  {
    "ticker": "TECHM.NS",
    "name": "TECH MAHINDRA LIMITED",
    "sector": "Technology",
    "price": 1473.8,
    "score": 66.32,
    "category": "Non-Banking",
    "metrics": {
      "roe": 16.61,
      "roa": 9.52,
      "pe": 27.18,
      "pb": 4.75,
      "ev_ebitda": 13.82,
      "growth": 12.6,
      "margins": 15.9,
      "de": 7.0,
      "momentum": -1.41
    },
    "rank": 10,
    "percentiles": {
      "roe": 58.3,
      "roa": 70.8,
      "pe": 54.2,
      "pb": 45.8,
      "ev_ebitda": 54.2,
      "growth": 54.2,
      "margins": 37.5,
      "de": 75.0,
      "momentum": 45.8
    }
  },
  {
    "ticker": "HINDUNILVR.NS",
    "name": "HINDUSTAN UNILEVER LTD.",
    "sector": "Consumer Defensive",
    "price": 2254.0,
    "score": 64.66,
    "category": "Non-Banking",
    "metrics": {
      "roe": 21.6,
      "roa": 10.74,
      "pe": 52.43,
      "pb": 10.87,
      "ev_ebitda": 34.52,
      "growth": 4.3,
      "margins": 23.51,
      "de": 3.0,
      "momentum": -4.16
    },
    "rank": 11,
    "percentiles": {
      "roe": 66.7,
      "roa": 75.0,
      "pe": 20.8,
      "pb": 12.5,
      "ev_ebitda": 70.8,
      "growth": 20.8,
      "margins": 70.8,
      "de": 79.2,
      "momentum": 37.5
    }
  },
  {
    "ticker": "BAJFINANCE.NS",
    "name": "BAJAJ FINANCE LIMITED",
    "sector": "Financial Services",
    "price": 939.7,
    "score": 63.6,
    "category": "Banking & Finance",
    "metrics": {
      "roe": 17.91,
      "roa": 3.77,
      "pe": 30.76,
      "pb": 5.12,
      "ev_ebitda": 0,
      "growth": 26.8,
      "margins": 0.0,
      "de": 313.0,
      "momentum": 4.9
    },
    "rank": 12,
    "percentiles": {
      "roe": 62.5,
      "roa": 33.3,
      "pe": 37.5,
      "pb": 41.7,
      "ev_ebitda": 0.0,
      "growth": 87.5,
      "margins": 0.0,
      "de": 4.2,
      "momentum": 66.7
    }
  },
  {
    "ticker": "BHARTIARTL.NS",
    "name": "BHARTI AIRTEL LIMITED",
    "sector": "Communication Services",
    "price": 1891.0,
    "score": 63.6,
    "category": "Non-Banking",
    "metrics": {
      "roe": 23.12,
      "roa": 7.77,
      "pe": 37.39,
      "pb": 9.23,
      "ev_ebitda": 12.88,
      "growth": 19.6,
      "margins": 52.03,
      "de": 117.0,
      "momentum": 1.11
    },
    "rank": 13,
    "percentiles": {
      "roe": 70.8,
      "roa": 62.5,
      "pe": 29.2,
      "pb": 20.8,
      "ev_ebitda": 50.0,
      "growth": 70.8,
      "margins": 91.7,
      "de": 20.8,
      "momentum": 58.3
    }
  },
  {
    "ticker": "MARUTI.NS",
    "name": "MARUTI SUZUKI INDIA LTD.",
    "sector": "Consumer Cyclical",
    "price": 13320.0,
    "score": 60.55,
    "category": "Non-Banking",
    "metrics": {
      "roe": 14.43,
      "roa": 6.55,
      "pe": 28.5,
      "pb": 4.2,
      "ev_ebitda": 18.71,
      "growth": 28.2,
      "margins": 11.7,
      "de": 0.0,
      "momentum": 6.87
    },
    "rank": 14,
    "percentiles": {
      "roe": 29.2,
      "roa": 45.8,
      "pe": 50.0,
      "pb": 58.3,
      "ev_ebitda": 58.3,
      "growth": 91.7,
      "margins": 29.2,
      "de": 100.0,
      "momentum": 70.8
    }
  },
  {
    "ticker": "RELIANCE.NS",
    "name": "RELIANCE INDUSTRIES LTD",
    "sector": "Energy",
    "price": 1436.0,
    "score": 59.3,
    "category": "Non-Banking",
    "metrics": {
      "roe": 9.14,
      "roa": 3.67,
      "pe": 24.07,
      "pb": 2.22,
      "ev_ebitda": 12.7,
      "growth": 12.5,
      "margins": 16.93,
      "de": 37.0,
      "momentum": -0.03
    },
    "rank": 15,
    "percentiles": {
      "roe": 0.0,
      "roa": 29.2,
      "pe": 58.3,
      "pb": 91.7,
      "ev_ebitda": 41.7,
      "growth": 50.0,
      "margins": 41.7,
      "de": 29.2,
      "momentum": 54.2
    }
  },
  {
    "ticker": "ICICIBANK.NS",
    "name": "ICICI BANK LTD.",
    "sector": "Financial Services",
    "price": 1265.7,
    "score": 57.54,
    "category": "Banking & Finance",
    "metrics": {
      "roe": 16.36,
      "roa": 2.08,
      "pe": 16.92,
      "pb": 2.5,
      "ev_ebitda": 0,
      "growth": 66.9,
      "margins": 0.0,
      "de": 0,
      "momentum": -11.61
    },
    "rank": 16,
    "percentiles": {
      "roe": 50.0,
      "roa": 16.7,
      "pe": 83.3,
      "pb": 79.2,
      "ev_ebitda": 0.0,
      "growth": 95.8,
      "margins": 0.0,
      "de": 100.0,
      "momentum": 33.3
    }
  },
  {
    "ticker": "TRENT.NS",
    "name": "TRENT LTD",
    "sector": "Consumer Cyclical",
    "price": 4148.0,
    "score": 54.34,
    "category": "Non-Banking",
    "metrics": {
      "roe": 27.13,
      "roa": 13.67,
      "pe": 85.54,
      "pb": 21.11,
      "ev_ebitda": 40.59,
      "growth": 19.2,
      "margins": 18.3,
      "de": 36.0,
      "momentum": -22.83
    },
    "rank": 17,
    "percentiles": {
      "roe": 79.2,
      "roa": 83.3,
      "pe": 4.2,
      "pb": 8.3,
      "ev_ebitda": 75.0,
      "growth": 66.7,
      "margins": 45.8,
      "de": 33.3,
      "momentum": 8.3
    }
  },
  {
    "ticker": "HCLTECH.NS",
    "name": "HCL TECHNOLOGIES LTD",
    "sector": "Technology",
    "price": 1201.4,
    "score": 54.26,
    "category": "Non-Banking",
    "metrics": {
      "roe": 23.36,
      "roa": 12.83,
      "pe": 19.57,
      "pb": 4.33,
      "ev_ebitda": 1118.64,
      "growth": 5.3,
      "margins": 19.76,
      "de": 7.0,
      "momentum": -23.56
    },
    "rank": 18,
    "percentiles": {
      "roe": 75.0,
      "roa": 79.2,
      "pe": 62.5,
      "pb": 54.2,
      "ev_ebitda": 95.8,
      "growth": 29.2,
      "margins": 58.3,
      "de": 75.0,
      "momentum": 4.2
    }
  },
  {
    "ticker": "INFY.NS",
    "name": "INFOSYS LIMITED",
    "sector": "Technology",
    "price": 1182.6,
    "score": 54.18,
    "category": "Non-Banking",
    "metrics": {
      "roe": 31.44,
      "roa": 15.09,
      "pe": 15.61,
      "pb": 5.55,
      "ev_ebitda": 1079.49,
      "growth": 6.6,
      "margins": 21.97,
      "de": 10.0,
      "momentum": -21.66
    },
    "rank": 19,
    "percentiles": {
      "roe": 87.5,
      "roa": 87.5,
      "pe": 91.7,
      "pb": 33.3,
      "ev_ebitda": 91.7,
      "growth": 37.5,
      "margins": 62.5,
      "de": 62.5,
      "momentum": 12.5
    }
  },
  {
    "ticker": "BAJAJFINSV.NS",
    "name": "BAJAJ FINSERV LTD.",
    "sector": "Financial Services",
    "price": 1741.7,
    "score": 53.32,
    "category": "Banking & Finance",
    "metrics": {
      "roe": 14.6,
      "roa": 4.92,
      "pe": 29.06,
      "pb": 3.62,
      "ev_ebitda": 12.08,
      "growth": 5.3,
      "margins": 38.04,
      "de": 256.0,
      "momentum": -13.77
    },
    "rank": 20,
    "percentiles": {
      "roe": 33.3,
      "roa": 37.5,
      "pe": 41.7,
      "pb": 66.7,
      "ev_ebitda": 37.5,
      "growth": 29.2,
      "margins": 87.5,
      "de": 12.5,
      "momentum": 29.2
    }
  },
  {
    "ticker": "HDFCBANK.NS",
    "name": "HDFC BANK LTD",
    "sector": "Financial Services",
    "price": 774.75,
    "score": 52.11,
    "category": "Banking & Finance",
    "metrics": {
      "roe": 13.82,
      "roa": 1.7,
      "pe": 17.28,
      "pb": 2.11,
      "ev_ebitda": 0,
      "growth": -1.8,
      "margins": 0.0,
      "de": 0,
      "momentum": -20.31
    },
    "rank": 21,
    "percentiles": {
      "roe": 25.0,
      "roa": 12.5,
      "pe": 79.2,
      "pb": 95.8,
      "ev_ebitda": 0.0,
      "growth": 12.5,
      "margins": 0.0,
      "de": 100.0,
      "momentum": 20.8
    }
  },
  {
    "ticker": "SBILIFE.NS",
    "name": "SBI LIFE INSURANCE CO LTD",
    "sector": "Financial Services",
    "price": 1820.0,
    "score": 43.76,
    "category": "Non-Banking",
    "metrics": {
      "roe": 13.7,
      "roa": 0.35,
      "pe": 74.1,
      "pb": 9.6,
      "ev_ebitda": 64.69,
      "growth": -82.2,
      "margins": 2.47,
      "de": 0,
      "momentum": 2.77
    },
    "rank": 22,
    "percentiles": {
      "roe": 20.8,
      "roa": 0.0,
      "pe": 12.5,
      "pb": 16.7,
      "ev_ebitda": 87.5,
      "growth": 0.0,
      "margins": 25.0,
      "de": 100.0,
      "momentum": 62.5
    }
  },
  {
    "ticker": "ADANIENT.NS",
    "name": "ADANI ENTERPRISES LIMITED",
    "sector": "Energy",
    "price": 2410.5,
    "score": 43.73,
    "category": "Non-Banking",
    "metrics": {
      "roe": 13.66,
      "roa": 2.14,
      "pe": 32.71,
      "pb": 3.84,
      "ev_ebitda": 29.41,
      "growth": 20.3,
      "margins": 13.92,
      "de": 120.0,
      "momentum": -1.92
    },
    "rank": 23,
    "percentiles": {
      "roe": 16.7,
      "roa": 20.8,
      "pe": 33.3,
      "pb": 62.5,
      "ev_ebitda": 66.7,
      "growth": 75.0,
      "margins": 33.3,
      "de": 16.7,
      "momentum": 41.7
    }
  },
  {
    "ticker": "HDFCLIFE.NS",
    "name": "HDFC LIFE INS CO LTD",
    "sector": "Financial Services",
    "price": 589.0,
    "score": 32.99,
    "category": "Non-Banking",
    "metrics": {
      "roe": 11.28,
      "roa": 0.35,
      "pe": 66.48,
      "pb": 7.15,
      "ev_ebitda": 60.01,
      "growth": -17.7,
      "margins": 2.13,
      "de": 17.0,
      "momentum": -20.57
    },
    "rank": 24,
    "percentiles": {
      "roe": 8.3,
      "roa": 0.0,
      "pe": 16.7,
      "pb": 29.2,
      "ev_ebitda": 83.3,
      "growth": 4.2,
      "margins": 20.8,
      "de": 50.0,
      "momentum": 16.7
    }
  }
]